psyco_full.py
Dcon-0.1.9.data/scripts/Dcon.py
Dcon-0.1.9.dist-info/DESCRIPTION.rst
Dcon-0.1.9.dist-info/METADATA
Dcon-0.1.9.dist-info/RECORD
Dcon-0.1.9.dist-info/WHEEL
Dcon-0.1.9.dist-info/metadata.json
Dcon-0.1.9.dist-info/top_level.txt
DconModule/__init__.py
DconModule/bam_cigar.py
DconModule/bgmm.py
DconModule/ireader.py
DconModule/iupac.py
DconModule/mystat.py
DconModule/utils.py
