Metadata-Version: 2.0
Name: Dcon
Version: 0.1.9
Summary: A program to assess DNA contamination level
Home-page: UNKNOWN
Author: Liguo Wang
Author-email: wangliguo78@gmail.com
License: MIT
Keywords: DNA contamination,Capture gene panel sequencing,Whole exome sequencing,whole genome sequencing
Platform: Linux
Platform: MacOS
Classifier: Development Status :: 5 - Production/Stable
Classifier: Environment :: Console
Classifier: Intended Audience :: Science/Research
Classifier: License :: OSI Approved :: GNU General Public License v2 (GPLv2)
Classifier: Operating System :: MacOS :: MacOS X
Classifier: Operating System :: POSIX
Classifier: Programming Language :: Python
Classifier: Topic :: Scientific/Engineering :: Bio-Informatics
Requires-Python: >=2.6, !=3.0.*, !=3.1.*, !=3.2.*, <4
Requires-Dist: numpy (>=1.13.3)
Requires-Dist: pysam (>=0.13)
Requires-Dist: scipy
Requires-Dist: sklearn
